{
"type": "FeatureCollection",
"name": "E02004056",
"crs": { "type": "name", "properties": { "name": "urn:ogc:def:crs:OGC:1.3:CRS84" } },
"features": [
{ "type": "Feature", "properties": { "id": "way/42593180", "name": null, "way_type": "shared footway", "index": 7, "index_10": 0, "stress_level": 1, "offset": null, "side": null, "proc_width": 0.5, "proc_surface": "dirt", "proc_smoothness": "very_bad", "proc_oneway": "no", "proc_sidepath": "no", "proc_highway": null, "proc_maxspeed": null, "proc_traffic_mode_left": null, "proc_traffic_mode_right": null, "proc_separation_left": "no", "proc_separation_right": "no", "proc_buffer_left": null, "proc_buffer_right": null, "proc_mandatory": null, "proc_traffic_sign": null, "fac_width": 0.097, "fac_surface": 0.2, "fac_highway": 1.0, "fac_maxspeed": 1.0, "base_index": 50, "fac_1": 0.15, "fac_2": 1.0, "fac_3": 1.0, "fac_4": 1.0, "data_bonus": "", "data_malus": "narrow width;bad surface", "data_incompleteness": 15.0, "data_missing": "lit", "data_missing_width": null, "data_missing_surface": null, "data_missing_smoothness": null, "data_missing_maxspeed": null, "data_missing_parking": null, "data_missing_lit": 1.0, "filter_usable": 1, "filter_way_type": "separated", "msoa": "E02004056", "msoa_threshold_score": 0.0, "index_space_syntax_length": 38.088030806813265, "index_space_syntax": 0.028, "index_length": 9522.0077017033145, "length": 1360.2868145290449, "index_space_syntax_length_norm": -0.31989317795030464 }, "geometry": { "type": "LineString", "coordinates": [ [ -1.3337962, 53.2779948 ], [ -1.333540399999988, 53.278134799999989 ], [ -1.3333602, 53.278150099999984 ], [ -1.3324246, 53.2788943 ], [ -1.3321242, 53.279115 ], [ -1.3319354, 53.2793151 ], [ -1.3318118, 53.2795892 ], [ -1.3317742, 53.2797909 ], [ -1.3318131, 53.280000199999989 ], [ -1.3317637, 53.2801567 ], [ -1.331896199999989, 53.2804765 ], [ -1.33215, 53.2807777 ], [ -1.3323731, 53.2809214 ], [ -1.3324412, 53.2809626 ], [ -1.3325446, 53.281085399999988 ], [ -1.3326691, 53.281387 ], [ -1.3327441, 53.281648599999983 ], [ -1.3327084, 53.2818874 ], [ -1.3326553, 53.2822583 ], [ -1.33268, 53.2826878 ], [ -1.3327334, 53.2831426 ], [ -1.3328018, 53.283409399999989 ], [ -1.332939599999989, 53.283887399999976 ], [ -1.3330684, 53.2841029 ], [ -1.33324, 53.284441599999987 ], [ -1.3332897, 53.2847144 ], [ -1.3333259, 53.285016299999981 ], [ -1.3332553, 53.2853736 ], [ -1.3331126, 53.2856572 ], [ -1.3329835, 53.2859058 ], [ -1.3329191, 53.2861214 ], [ -1.3329103, 53.2863678 ], [ -1.3328806, 53.2867159 ], [ -1.3329257, 53.2869736 ], [ -1.3330753, 53.287337499999985 ], [ -1.3332381, 53.287659 ], [ -1.3335252, 53.2880877 ], [ -1.3337121, 53.2883772 ], [ -1.3339546, 53.2887473 ], [ -1.3341175, 53.289023299999975 ], [ -1.3342499, 53.2892803 ], [ -1.3342968, 53.289404599999983 ] ] } },
{ "type": "Feature", "properties": { "id": "way/42594348", "name": null, "way_type": "shared path", "index": 32, "index_10": 3, "stress_level": 1, "offset": null, "side": null, "proc_width": 1.5, "proc_surface": "gravel", "proc_smoothness": "intermediate", "proc_oneway": "no", "proc_sidepath": "no", "proc_highway": null, "proc_maxspeed": null, "proc_traffic_mode_left": null, "proc_traffic_mode_right": null, "proc_separation_left": "no", "proc_separation_right": "no", "proc_buffer_left": null, "proc_buffer_right": null, "proc_mandatory": null, "proc_traffic_sign": null, "fac_width": 0.29, "fac_surface": 0.7, "fac_highway": 1.0, "fac_maxspeed": 1.0, "base_index": 70, "fac_1": 0.45, "fac_2": 1.0, "fac_3": 1.0, "fac_4": 1.0, "data_bonus": "", "data_malus": "narrow width", "data_incompleteness": 15.0, "data_missing": "lit", "data_missing_width": null, "data_missing_surface": null, "data_missing_smoothness": null, "data_missing_maxspeed": null, "data_missing_parking": null, "data_missing_lit": 1.0, "filter_usable": 1, "filter_way_type": "separated", "msoa": "E02004056", "msoa_threshold_score": 0.0, "index_space_syntax_length": 41.928047278065527, "index_space_syntax": 0.20854182739870994, "index_length": 6433.7093888264108, "length": 201.05341840082534, "index_space_syntax_length_norm": -0.27985374968810417 }, "geometry": { "type": "LineString", "coordinates": [ [ -1.3321242, 53.279115 ], [ -1.3320443, 53.2790688 ], [ -1.3319806, 53.279032 ], [ -1.3316434, 53.2788569 ], [ -1.3312439, 53.2786839 ], [ -1.3307262, 53.2785693 ], [ -1.3301958, 53.278548699999988 ], [ -1.3297569, 53.278496 ], [ -1.3295568, 53.2784347 ], [ -1.3294758, 53.278380899999981 ] ] } },
{ "type": "Feature", "properties": { "id": "way/42594353", "name": null, "way_type": "track or service", "index": 13, "index_10": 1, "stress_level": 2, "offset": null, "side": null, "proc_width": 3.2, "proc_surface": "dirt", "proc_smoothness": null, "proc_oneway": "no", "proc_sidepath": null, "proc_highway": "track", "proc_maxspeed": null, "proc_traffic_mode_left": null, "proc_traffic_mode_right": null, "proc_separation_left": "no", "proc_separation_right": "no", "proc_buffer_left": null, "proc_buffer_right": null, "proc_mandatory": null, "proc_traffic_sign": null, "fac_width": null, "fac_surface": 0.2, "fac_highway": 1.0, "fac_maxspeed": 1.0, "base_index": 65, "fac_1": 0.2, "fac_2": 1.0, "fac_3": 1.0, "fac_4": 1.0, "data_bonus": "", "data_malus": "bad surface", "data_incompleteness": 50.0, "data_missing": "width;smoothness;lit", "data_missing_width": 1.0, "data_missing_surface": null, "data_missing_smoothness": 1.0, "data_missing_maxspeed": null, "data_missing_parking": null, "data_missing_lit": 1.0, "filter_usable": 1, "filter_way_type": "shared traffic", "msoa": "E02004056", "msoa_threshold_score": 0.0, "index_space_syntax_length": 13.569672773570332, "index_space_syntax": 0.05545870956205648, "index_length": 3180.8483725900987, "length": 244.68064404539223, "index_space_syntax_length_norm": -0.57554339323670822 }, "geometry": { "type": "LineString", "coordinates": [ [ -1.3299467, 53.2814728 ], [ -1.3306171, 53.2812742 ], [ -1.3308638, 53.2812273 ], [ -1.3313641, 53.2811299 ], [ -1.3318918, 53.281065299999987 ], [ -1.3321285, 53.28103 ], [ -1.3323485, 53.28098940000001 ], [ -1.3324412, 53.2809626 ], [ -1.332665, 53.280906 ], [ -1.3334119, 53.2807746 ] ] } },
{ "type": "Feature", "properties": { "id": "way/42602070", "name": null, "way_type": "shared path", "index": 35, "index_10": 3, "stress_level": 1, "offset": null, "side": null, "proc_width": 4.0, "proc_surface": "gravel", "proc_smoothness": "bad", "proc_oneway": "no", "proc_sidepath": "no", "proc_highway": null, "proc_maxspeed": null, "proc_traffic_mode_left": null, "proc_traffic_mode_right": null, "proc_separation_left": "no", "proc_separation_right": "no", "proc_buffer_left": null, "proc_buffer_right": null, "proc_mandatory": null, "proc_traffic_sign": null, "fac_width": 0.996, "fac_surface": 0.3, "fac_highway": 1.0, "fac_maxspeed": 1.0, "base_index": 70, "fac_1": 0.51, "fac_2": 1.0, "fac_3": 1.0, "fac_4": 1.0, "data_bonus": "", "data_malus": "bad surface", "data_incompleteness": 15.0, "data_missing": "lit", "data_missing_width": null, "data_missing_surface": null, "data_missing_smoothness": null, "data_missing_maxspeed": null, "data_missing_parking": null, "data_missing_lit": 1.0, "filter_usable": 1, "filter_way_type": "separated", "msoa": "E02004056", "msoa_threshold_score": 0.0, "index_space_syntax_length": 352.40614274689779, "index_space_syntax": 0.36340775377709772, "index_length": 33940.428810186648, "length": 969.72653743390424, "index_space_syntax_length_norm": 2.9574671117130338 }, "geometry": { "type": "LineString", "coordinates": [ [ -1.3368309, 53.288043899999984 ], [ -1.3369703, 53.2876166 ], [ -1.3370554, 53.287421099999982 ], [ -1.3373735, 53.2867347 ], [ -1.3375793, 53.2863575 ], [ -1.3379011, 53.285801799999987 ], [ -1.3387447, 53.284334799999989 ], [ -1.3388305, 53.2842219 ], [ -1.3393627, 53.2832623 ], [ -1.3396845, 53.282644299999987 ], [ -1.3399882, 53.2821482 ], [ -1.3405225, 53.281223599999983 ], [ -1.3411909, 53.280096099999987 ], [ -1.3413432, 53.27976469999998 ] ] } },
{ "type": "Feature", "properties": { "id": "way/42602085", "name": null, "way_type": "shared path", "index": 35, "index_10": 3, "stress_level": 1, "offset": null, "side": null, "proc_width": 4.0, "proc_surface": "gravel", "proc_smoothness": "bad", "proc_oneway": "no", "proc_sidepath": "no", "proc_highway": null, "proc_maxspeed": null, "proc_traffic_mode_left": null, "proc_traffic_mode_right": null, "proc_separation_left": "no", "proc_separation_right": "no", "proc_buffer_left": null, "proc_buffer_right": null, "proc_mandatory": null, "proc_traffic_sign": null, "fac_width": 0.996, "fac_surface": 0.3, "fac_highway": 1.0, "fac_maxspeed": 1.0, "base_index": 70, "fac_1": 0.51, "fac_2": 1.0, "fac_3": 1.0, "fac_4": 1.0, "data_bonus": "", "data_malus": "bad surface", "data_incompleteness": 15.0, "data_missing": "lit", "data_missing_width": null, "data_missing_surface": null, "data_missing_smoothness": null, "data_missing_maxspeed": null, "data_missing_parking": null, "data_missing_lit": 1.0, "filter_usable": 1, "filter_way_type": "separated", "msoa": "E02004056", "msoa_threshold_score": 0.0, "index_space_syntax_length": 242.91072419661023, "index_space_syntax": 0.36388945981548815, "index_length": 23363.895593986905, "length": 667.53987411391154, "index_space_syntax_length_norm": 1.8157704578301543 }, "geometry": { "type": "LineString", "coordinates": [ [ -1.3413781, 53.2797033 ], [ -1.3414756, 53.2795219 ], [ -1.3415836, 53.2793419 ], [ -1.3419902, 53.2786809 ], [ -1.3423259, 53.278201699999983 ], [ -1.3427702, 53.277453099999988 ], [ -1.3429333, 53.2772889 ], [ -1.3434912, 53.2763189 ], [ -1.3436628, 53.2760366 ], [ -1.3437744, 53.275713299999985 ], [ -1.3437776, 53.2755544 ], [ -1.344255, 53.274640599999984 ], [ -1.3445469, 53.2740298 ] ] } },
{ "type": "Feature", "properties": { "id": "way/42602089", "name": null, "way_type": "shared path", "index": 54, "index_10": 5, "stress_level": 1, "offset": null, "side": null, "proc_width": 3.2, "proc_surface": "paving_stones", "proc_smoothness": null, "proc_oneway": "no", "proc_sidepath": "no", "proc_highway": null, "proc_maxspeed": null, "proc_traffic_mode_left": null, "proc_traffic_mode_right": null, "proc_separation_left": "no", "proc_separation_right": "no", "proc_buffer_left": null, "proc_buffer_right": null, "proc_mandatory": null, "proc_traffic_sign": null, "fac_width": 0.846, "fac_surface": 0.7, "fac_highway": 1.0, "fac_maxspeed": 1.0, "base_index": 70, "fac_1": 0.77, "fac_2": 1.0, "fac_3": 1.0, "fac_4": 1.0, "data_bonus": "", "data_malus": "", "data_incompleteness": 80.0, "data_missing": "width;surface;smoothness;lit", "data_missing_width": 1.0, "data_missing_surface": 1.0, "data_missing_smoothness": 1.0, "data_missing_maxspeed": null, "data_missing_parking": null, "data_missing_lit": 1.0, "filter_usable": 1, "filter_way_type": "separated", "msoa": "E02004056", "msoa_threshold_score": 0.0, "index_space_syntax_length": 4.7688464238982293, "index_space_syntax": 0.66083059276353684, "index_length": 389.68793168849436, "length": 7.2164431794165624, "index_space_syntax_length_norm": -0.66730863901464244 }, "geometry": { "type": "LineString", "coordinates": [ [ -1.3413432, 53.27976469999998 ], [ -1.3413781, 53.2797033 ] ] } },
{ "type": "Feature", "properties": { "id": "way/59582865", "name": "Renishaw Road", "way_type": "shared traffic lane", "index": 15, "index_10": 1, "stress_level": 4, "offset": null, "side": null, "proc_width": 3.2, "proc_surface": "asphalt", "proc_smoothness": null, "proc_oneway": "no", "proc_sidepath": null, "proc_highway": "secondary", "proc_maxspeed": 60.0, "proc_traffic_mode_left": "motor_vehicle", "proc_traffic_mode_right": null, "proc_separation_left": "no", "proc_separation_right": "no", "proc_buffer_left": null, "proc_buffer_right": null, "proc_mandatory": null, "proc_traffic_sign": null, "fac_width": 0.668, "fac_surface": 1.0, "fac_highway": 0.65, "fac_maxspeed": 0.5, "base_index": 60, "fac_1": 0.79, "fac_2": 0.33, "fac_3": 1.0, "fac_4": 1.0, "data_bonus": "", "data_malus": "along a major road;along a road with high speed limits", "data_incompleteness": 65.0, "data_missing": "width:lanes;surface;smoothness;lit", "data_missing_width": null, "data_missing_surface": 1.0, "data_missing_smoothness": 1.0, "data_missing_maxspeed": null, "data_missing_parking": null, "data_missing_lit": 1.0, "filter_usable": 1, "filter_way_type": "shared traffic", "msoa": "E02004056", "msoa_threshold_score": 0.0, "index_space_syntax_length": 22.770953195896034, "index_space_syntax": 0.1436561109341162, "index_length": 2377.652406969929, "length": 158.51016046466194, "index_space_syntax_length_norm": -0.47960265700597104 }, "geometry": { "type": "LineString", "coordinates": [ [ -1.322801, 53.2818062 ], [ -1.3227153, 53.281698299999988 ], [ -1.3226377, 53.2815734 ], [ -1.3225418, 53.281403 ], [ -1.3222917, 53.280939199999978 ], [ -1.3222106, 53.2807405 ], [ -1.3221889, 53.2806379 ], [ -1.3221802, 53.280541499999984 ], [ -1.3221835, 53.2804413 ] ] } },
{ "type": "Feature", "properties": { "id": "way/77839861", "name": null, "way_type": "shared path", "index": 32, "index_10": 3, "stress_level": 1, "offset": null, "side": null, "proc_width": 1.5, "proc_surface": "gravel", "proc_smoothness": "intermediate", "proc_oneway": "no", "proc_sidepath": "no", "proc_highway": null, "proc_maxspeed": null, "proc_traffic_mode_left": null, "proc_traffic_mode_right": null, "proc_separation_left": "no", "proc_separation_right": "no", "proc_buffer_left": null, "proc_buffer_right": null, "proc_mandatory": null, "proc_traffic_sign": null, "fac_width": 0.29, "fac_surface": 0.7, "fac_highway": 1.0, "fac_maxspeed": 1.0, "base_index": 70, "fac_1": 0.45, "fac_2": 1.0, "fac_3": 1.0, "fac_4": 1.0, "data_bonus": "", "data_malus": "narrow width", "data_incompleteness": 15.0, "data_missing": "lit", "data_missing_width": null, "data_missing_surface": null, "data_missing_smoothness": null, "data_missing_maxspeed": null, "data_missing_parking": null, "data_missing_lit": 1.0, "filter_usable": 1, "filter_way_type": "separated", "msoa": "E02004056", "msoa_threshold_score": 0.0, "index_space_syntax_length": 164.10983992562458, "index_space_syntax": 0.20662522850557302, "index_length": 25415.651881436854, "length": 794.23912129490168, "index_space_syntax_length_norm": 0.99412232783211518 }, "geometry": { "type": "LineString", "coordinates": [ [ -1.3296099, 53.271466 ], [ -1.3297109, 53.2717583 ], [ -1.329854, 53.2721354 ], [ -1.3299452, 53.272364799999977 ], [ -1.330023, 53.272599 ], [ -1.3300466, 53.272663099999988 ], [ -1.3300686, 53.2728075 ], [ -1.3300579, 53.272966299999986 ], [ -1.3299667, 53.2731876 ], [ -1.3298808, 53.273380099999983 ], [ -1.3297897, 53.273554899999986 ], [ -1.3297655, 53.273635099999986 ], [ -1.3297762, 53.2737282 ], [ -1.3298031, 53.2738469 ], [ -1.3298352, 53.2739479 ], [ -1.329846, 53.2740907 ], [ -1.3298138, 53.274227 ], [ -1.3297521, 53.2743729 ], [ -1.3296394, 53.274571799999983 ], [ -1.3294732, 53.2748702 ], [ -1.3293578, 53.2751669 ], [ -1.3292559, 53.275434699999984 ], [ -1.3291888, 53.2756256 ], [ -1.3291352, 53.275907899999986 ], [ -1.3290697, 53.2762072 ], [ -1.3290618, 53.276243199999989 ], [ -1.3289743, 53.2765687 ], [ -1.3288965, 53.2768814 ], [ -1.3288589, 53.2771781 ], [ -1.3288589, 53.277508499999989 ], [ -1.3288831, 53.277646399999981 ], [ -1.3289501, 53.27781 ], [ -1.329036, 53.278000899999988 ], [ -1.3291191, 53.278142 ], [ -1.3292961, 53.2782478 ], [ -1.3294758, 53.278380899999981 ] ] } },
{ "type": "Feature", "properties": { "id": "way/163510895", "name": "Renishaw Road", "way_type": "shared traffic lane", "index": 15, "index_10": 1, "stress_level": 4, "offset": null, "side": null, "proc_width": 3.2, "proc_surface": "asphalt", "proc_smoothness": null, "proc_oneway": "no", "proc_sidepath": null, "proc_highway": "secondary", "proc_maxspeed": 60.0, "proc_traffic_mode_left": "motor_vehicle", "proc_traffic_mode_right": null, "proc_separation_left": "no", "proc_separation_right": "no", "proc_buffer_left": null, "proc_buffer_right": null, "proc_mandatory": null, "proc_traffic_sign": null, "fac_width": 0.668, "fac_surface": 1.0, "fac_highway": 0.65, "fac_maxspeed": 0.5, "base_index": 60, "fac_1": 0.79, "fac_2": 0.33, "fac_3": 1.0, "fac_4": 1.0, "data_bonus": "", "data_malus": "along a major road;along a road with high speed limits", "data_incompleteness": 65.0, "data_missing": "width:lanes;surface;smoothness;lit", "data_missing_width": null, "data_missing_surface": 1.0, "data_missing_smoothness": 1.0, "data_missing_maxspeed": null, "data_missing_parking": null, "data_missing_lit": 1.0, "filter_usable": 1, "filter_way_type": "shared traffic", "msoa": "E02004056", "msoa_threshold_score": 0.0, "index_space_syntax_length": 41.634549042914045, "index_space_syntax": 0.14216286167324255, "index_length": 4392.9773802608779, "length": 292.86515868405854, "index_space_syntax_length_norm": -0.28291402341854421 }, "geometry": { "type": "LineString", "coordinates": [ [ -1.3221835, 53.2804413 ], [ -1.322178, 53.28019089999998 ], [ -1.3221701, 53.2801211 ], [ -1.3221482, 53.2800516 ], [ -1.3220652, 53.2798942 ], [ -1.3219042, 53.2796397 ], [ -1.3207858, 53.277964799999978 ] ] } },
{ "type": "Feature", "properties": { "id": "way/163510898", "name": null, "way_type": "track or service", "index": 15, "index_10": 1, "stress_level": 2, "offset": null, "side": null, "proc_width": 4.0, "proc_surface": "gravel", "proc_smoothness": null, "proc_oneway": "no", "proc_sidepath": null, "proc_highway": "service", "proc_maxspeed": null, "proc_traffic_mode_left": null, "proc_traffic_mode_right": null, "proc_separation_left": "no", "proc_separation_right": "no", "proc_buffer_left": null, "proc_buffer_right": null, "proc_mandatory": null, "proc_traffic_sign": null, "fac_width": 0.25, "fac_surface": 0.2, "fac_highway": 1.0, "fac_maxspeed": 1.0, "base_index": 65, "fac_1": 0.22, "fac_2": 1.0, "fac_3": 1.0, "fac_4": 1.0, "data_bonus": "", "data_malus": "narrow width;bad surface", "data_incompleteness": 50.0, "data_missing": "width;smoothness;lit", "data_missing_width": 1.0, "data_missing_surface": null, "data_missing_smoothness": 1.0, "data_missing_maxspeed": null, "data_missing_parking": null, "data_missing_lit": 1.0, "filter_usable": 1, "filter_way_type": "shared traffic", "msoa": "E02004056", "msoa_threshold_score": 0.0, "index_space_syntax_length": 6.421323026346732, "index_space_syntax": 0.070584096250536132, "index_length": 1364.611159053685, "length": 90.974077270245672, "index_space_syntax_length_norm": -0.65007844771884182 }, "geometry": { "type": "LineString", "coordinates": [ [ -1.3219042, 53.2796397 ], [ -1.3221694, 53.2795951 ], [ -1.322473, 53.279544199999989 ], [ -1.3226376, 53.27951130000001 ], [ -1.3228127, 53.2794573 ], [ -1.3229647, 53.2794082 ], [ -1.3230575, 53.279383199999984 ], [ -1.3231863, 53.2793832 ] ] } },
{ "type": "Feature", "properties": { "id": "way/163862114", "name": null, "way_type": "track or service", "index": 18, "index_10": 1, "stress_level": 2, "offset": null, "side": null, "proc_width": 4.0, "proc_surface": "unpaved", "proc_smoothness": null, "proc_oneway": "no", "proc_sidepath": null, "proc_highway": "service", "proc_maxspeed": null, "proc_traffic_mode_left": null, "proc_traffic_mode_right": null, "proc_separation_left": "no", "proc_separation_right": "no", "proc_buffer_left": null, "proc_buffer_right": null, "proc_mandatory": null, "proc_traffic_sign": null, "fac_width": 0.25, "fac_surface": 0.3, "fac_highway": 1.0, "fac_maxspeed": 1.0, "base_index": 65, "fac_1": 0.27, "fac_2": 1.0, "fac_3": 1.0, "fac_4": 1.0, "data_bonus": "", "data_malus": "narrow width;bad surface", "data_incompleteness": 80.0, "data_missing": "width;surface;smoothness;lit", "data_missing_width": 1.0, "data_missing_surface": 1.0, "data_missing_smoothness": 1.0, "data_missing_maxspeed": null, "data_missing_parking": null, "data_missing_lit": 1.0, "filter_usable": 1, "filter_way_type": "shared traffic", "msoa": "E02004056", "msoa_threshold_score": 0.0, "index_space_syntax_length": 21.38208545326113, "index_space_syntax": 0.074853829329003724, "index_length": 5141.7214270636023, "length": 285.65119039242234, "index_space_syntax_length_norm": -0.49408422779172861 }, "geometry": { "type": "LineString", "coordinates": [ [ -1.3335379, 53.2898093 ], [ -1.3341762, 53.2895305 ], [ -1.3343321, 53.289478 ], [ -1.3343887, 53.289455899999986 ], [ -1.3351465, 53.289199099999976 ], [ -1.3358818, 53.2889607 ], [ -1.3361011, 53.288884599999989 ], [ -1.3362093, 53.2888339 ], [ -1.3362999, 53.288761299999983 ], [ -1.3363461, 53.288641499999983 ], [ -1.336438, 53.2882981 ], [ -1.3364796, 53.2881721 ] ] } },
{ "type": "Feature", "properties": { "id": "way/163862117", "name": null, "way_type": "track or service", "index": 18, "index_10": 1, "stress_level": 2, "offset": null, "side": null, "proc_width": 4.0, "proc_surface": "unpaved", "proc_smoothness": null, "proc_oneway": "no", "proc_sidepath": null, "proc_highway": "service", "proc_maxspeed": null, "proc_traffic_mode_left": null, "proc_traffic_mode_right": null, "proc_separation_left": "no", "proc_separation_right": "no", "proc_buffer_left": null, "proc_buffer_right": null, "proc_mandatory": null, "proc_traffic_sign": null, "fac_width": 0.25, "fac_surface": 0.3, "fac_highway": 1.0, "fac_maxspeed": 1.0, "base_index": 65, "fac_1": 0.27, "fac_2": 1.0, "fac_3": 1.0, "fac_4": 1.0, "data_bonus": "", "data_malus": "narrow width;bad surface", "data_incompleteness": 80.0, "data_missing": "width;surface;smoothness;lit", "data_missing_width": 1.0, "data_missing_surface": 1.0, "data_missing_smoothness": 1.0, "data_missing_maxspeed": null, "data_missing_parking": null, "data_missing_lit": 1.0, "filter_usable": 1, "filter_way_type": "shared traffic", "msoa": "E02004056", "msoa_threshold_score": 0.0, "index_space_syntax_length": 1.7798719552391267, "index_space_syntax": 0.447, "index_length": 71.672696184125897, "length": 3.9818164546736612, "index_space_syntax_length_norm": -0.69847434617016335 }, "geometry": { "type": "LineString", "coordinates": [ [ -1.3365085, 53.288081299999988 ], [ -1.3365173, 53.2880459 ] ] } },
{ "type": "Feature", "properties": { "id": "way/164015305", "name": null, "way_type": "track or service", "index": 13, "index_10": 1, "stress_level": 2, "offset": null, "side": null, "proc_width": 3.2, "proc_surface": "dirt", "proc_smoothness": null, "proc_oneway": "no", "proc_sidepath": null, "proc_highway": "track", "proc_maxspeed": null, "proc_traffic_mode_left": null, "proc_traffic_mode_right": null, "proc_separation_left": "no", "proc_separation_right": "no", "proc_buffer_left": null, "proc_buffer_right": null, "proc_mandatory": null, "proc_traffic_sign": null, "fac_width": null, "fac_surface": 0.2, "fac_highway": 1.0, "fac_maxspeed": 1.0, "base_index": 65, "fac_1": 0.2, "fac_2": 1.0, "fac_3": 1.0, "fac_4": 1.0, "data_bonus": "", "data_malus": "bad surface", "data_incompleteness": 50.0, "data_missing": "width;smoothness;lit", "data_missing_width": 1.0, "data_missing_surface": null, "data_missing_smoothness": 1.0, "data_missing_maxspeed": null, "data_missing_parking": null, "data_missing_lit": 1.0, "filter_usable": 1, "filter_way_type": "shared traffic", "msoa": "E02004056", "msoa_threshold_score": 0.0, "index_space_syntax_length": 6.0188724500032409, "index_space_syntax": 0.061844119703253854, "index_length": 1265.2026130452844, "length": 97.323277926560337, "index_space_syntax_length_norm": -0.65427475549544145 }, "geometry": { "type": "LineString", "coordinates": [ [ -1.3424588, 53.279897599999984 ], [ -1.3422243, 53.2798743 ], [ -1.3417829, 53.2798078 ], [ -1.34152, 53.279756399999989 ], [ -1.3410587, 53.279657 ] ] } },
{ "type": "Feature", "properties": { "id": "way/183618055", "name": null, "way_type": "track or service", "index": 13, "index_10": 1, "stress_level": 2, "offset": null, "side": null, "proc_width": 3.2, "proc_surface": "gravel", "proc_smoothness": null, "proc_oneway": "no", "proc_sidepath": null, "proc_highway": "track", "proc_maxspeed": null, "proc_traffic_mode_left": null, "proc_traffic_mode_right": null, "proc_separation_left": "no", "proc_separation_right": "no", "proc_buffer_left": null, "proc_buffer_right": null, "proc_mandatory": null, "proc_traffic_sign": null, "fac_width": null, "fac_surface": 0.2, "fac_highway": 1.0, "fac_maxspeed": 1.0, "base_index": 65, "fac_1": 0.2, "fac_2": 1.0, "fac_3": 1.0, "fac_4": 1.0, "data_bonus": "", "data_malus": "bad surface", "data_incompleteness": 50.0, "data_missing": "width;smoothness;lit", "data_missing_width": 1.0, "data_missing_surface": null, "data_missing_smoothness": 1.0, "data_missing_maxspeed": null, "data_missing_parking": null, "data_missing_lit": 1.0, "filter_usable": 1, "filter_way_type": "shared traffic", "msoa": "E02004056", "msoa_threshold_score": 0.0, "index_space_syntax_length": 3.2438845335366002, "index_space_syntax": 0.075145403398188509, "index_length": 561.18534240235886, "length": 43.168103261719914, "index_space_syntax_length_norm": -0.68320924847005249 }, "geometry": { "type": "LineString", "coordinates": [ [ -1.3256169, 53.280286099999984 ], [ -1.3256861, 53.280371899999977 ], [ -1.3257636, 53.280541299999989 ], [ -1.3258121, 53.280654699999985 ] ] } },
{ "type": "Feature", "properties": { "id": "way/224731443", "name": "Eckington Road", "way_type": "shared traffic lane", "index": 28, "index_10": 2, "stress_level": 4, "offset": null, "side": null, "proc_width": 3.2, "proc_surface": "asphalt", "proc_smoothness": null, "proc_oneway": "no", "proc_sidepath": null, "proc_highway": "secondary", "proc_maxspeed": null, "proc_traffic_mode_left": "motor_vehicle", "proc_traffic_mode_right": null, "proc_separation_left": "no", "proc_separation_right": "no", "proc_buffer_left": null, "proc_buffer_right": null, "proc_mandatory": null, "proc_traffic_sign": null, "fac_width": 0.668, "fac_surface": 1.0, "fac_highway": 0.65, "fac_maxspeed": 1.0, "base_index": 60, "fac_1": 0.79, "fac_2": 0.65, "fac_3": 1.0, "fac_4": 0.9, "data_bonus": "", "data_malus": "along a major road;no street lighting", "data_incompleteness": 65.0, "data_missing": "width:lanes;surface;smoothness;maxspeed", "data_missing_width": null, "data_missing_surface": 1.0, "data_missing_smoothness": 1.0, "data_missing_maxspeed": 1.0, "data_missing_parking": null, "data_missing_lit": null, "filter_usable": 1, "filter_way_type": "shared traffic", "msoa": "E02004056", "msoa_threshold_score": 0.0, "index_space_syntax_length": 104.98435643548937, "index_space_syntax": 0.26740442709196732, "index_length": 10992.944328414993, "length": 392.60515458624974, "index_space_syntax_length_norm": 0.37762743193934512 }, "geometry": { "type": "LineString", "coordinates": [ [ -1.3461231, 53.281518 ], [ -1.3461712, 53.281417599999983 ], [ -1.3462201, 53.281240699999977 ], [ -1.3462607, 53.2809923 ], [ -1.3463538, 53.280333499999983 ], [ -1.3464081, 53.280049299999988 ], [ -1.3465146, 53.2795535 ], [ -1.3467875, 53.278641699999987 ], [ -1.3469496, 53.2782081 ], [ -1.3470295, 53.278036899999982 ] ] } },
{ "type": "Feature", "properties": { "id": "way/224731444", "name": "Hawthorn Hill", "way_type": "shared traffic lane", "index": 31, "index_10": 3, "stress_level": 4, "offset": null, "side": null, "proc_width": 3.2, "proc_surface": "asphalt", "proc_smoothness": null, "proc_oneway": "no", "proc_sidepath": null, "proc_highway": "secondary", "proc_maxspeed": null, "proc_traffic_mode_left": "motor_vehicle", "proc_traffic_mode_right": null, "proc_separation_left": "no", "proc_separation_right": "no", "proc_buffer_left": null, "proc_buffer_right": null, "proc_mandatory": null, "proc_traffic_sign": null, "fac_width": 0.668, "fac_surface": 1.0, "fac_highway": 0.65, "fac_maxspeed": 1.0, "base_index": 60, "fac_1": 0.79, "fac_2": 0.65, "fac_3": 1.0, "fac_4": 1.0, "data_bonus": "", "data_malus": "along a major road", "data_incompleteness": 65.0, "data_missing": "width:lanes;surface;smoothness;maxspeed", "data_missing_width": null, "data_missing_surface": 1.0, "data_missing_smoothness": 1.0, "data_missing_maxspeed": 1.0, "data_missing_parking": null, "data_missing_lit": null, "filter_usable": 1, "filter_way_type": "shared traffic", "msoa": "E02004056", "msoa_threshold_score": 0.0, "index_space_syntax_length": 189.91845901449668, "index_space_syntax": 0.4423904193379532, "index_length": 13308.317658099662, "length": 429.30056961611814, "index_space_syntax_length_norm": 1.2632259528533807 }, "geometry": { "type": "LineString", "coordinates": [ [ -1.3454785, 53.2853229 ], [ -1.3454243, 53.285181199999982 ], [ -1.3453965, 53.285036 ], [ -1.3453627, 53.2847068 ], [ -1.3453657, 53.284098899999989 ], [ -1.3457616, 53.282253499999989 ], [ -1.3458145, 53.2820559 ], [ -1.3461231, 53.281518 ] ] } },
{ "type": "Feature", "properties": { "id": "way/258934774", "name": "Staveley Lane", "way_type": "shared traffic lane", "index": 31, "index_10": 3, "stress_level": 4, "offset": null, "side": null, "proc_width": 3.2, "proc_surface": "asphalt", "proc_smoothness": null, "proc_oneway": "no", "proc_sidepath": null, "proc_highway": "secondary", "proc_maxspeed": null, "proc_traffic_mode_left": "motor_vehicle", "proc_traffic_mode_right": null, "proc_separation_left": "no", "proc_separation_right": "no", "proc_buffer_left": null, "proc_buffer_right": null, "proc_mandatory": null, "proc_traffic_sign": null, "fac_width": 0.668, "fac_surface": 1.0, "fac_highway": 0.65, "fac_maxspeed": 1.0, "base_index": 60, "fac_1": 0.79, "fac_2": 0.65, "fac_3": 1.0, "fac_4": 1.0, "data_bonus": "", "data_malus": "along a major road", "data_incompleteness": 65.0, "data_missing": "width:lanes;surface;smoothness;maxspeed", "data_missing_width": null, "data_missing_surface": 1.0, "data_missing_smoothness": 1.0, "data_missing_maxspeed": 1.0, "data_missing_parking": null, "data_missing_lit": null, "filter_usable": 1, "filter_way_type": "shared traffic", "msoa": "E02004056", "msoa_threshold_score": 0.0, "index_space_syntax_length": 11.456432644616317, "index_space_syntax": 0.30417323044666378, "index_length": 1167.5893090972731, "length": 37.664171261202362, "index_space_syntax_length_norm": -0.59757791500959656 }, "geometry": { "type": "LineString", "coordinates": [ [ -1.3456253, 53.2856494 ], [ -1.3456053, 53.285581 ], [ -1.3455731, 53.285507199999977 ], [ -1.3454785, 53.2853229 ] ] } },
{ "type": "Feature", "properties": { "id": "way/698840339", "name": null, "way_type": "track or service", "index": 18, "index_10": 1, "stress_level": 2, "offset": null, "side": null, "proc_width": 4.0, "proc_surface": "unpaved", "proc_smoothness": null, "proc_oneway": "no", "proc_sidepath": null, "proc_highway": "service", "proc_maxspeed": null, "proc_traffic_mode_left": null, "proc_traffic_mode_right": null, "proc_separation_left": "no", "proc_separation_right": "no", "proc_buffer_left": null, "proc_buffer_right": null, "proc_mandatory": null, "proc_traffic_sign": null, "fac_width": 0.25, "fac_surface": 0.3, "fac_highway": 1.0, "fac_maxspeed": 1.0, "base_index": 65, "fac_1": 0.27, "fac_2": 1.0, "fac_3": 1.0, "fac_4": 1.0, "data_bonus": "", "data_malus": "narrow width;bad surface", "data_incompleteness": 80.0, "data_missing": "width;surface;smoothness;lit", "data_missing_width": 1.0, "data_missing_surface": 1.0, "data_missing_smoothness": 1.0, "data_missing_maxspeed": null, "data_missing_parking": null, "data_missing_lit": 1.0, "filter_usable": 1, "filter_way_type": "shared traffic", "msoa": "E02004056", "msoa_threshold_score": 0.0, "index_space_syntax_length": 31.386975513702779, "index_space_syntax": 0.073663195800583142, "index_length": 7669.5770948642112, "length": 426.08761638134507, "index_space_syntax_length_norm": -0.38976434248779396 }, "geometry": { "type": "LineString", "coordinates": [ [ -1.3251285, 53.2834382 ], [ -1.3257715, 53.2832219 ], [ -1.3279678, 53.2825818 ], [ -1.3294767, 53.2821406 ], [ -1.3295894, 53.282104 ], [ -1.3297304, 53.2820237 ], [ -1.3299741, 53.281799599999985 ], [ -1.3299327, 53.281638 ], [ -1.3299467, 53.2814728 ], [ -1.3299575, 53.281344599999983 ] ] } },
{ "type": "Feature", "properties": { "id": "way/922883121", "name": null, "way_type": "track or service", "index": 18, "index_10": 1, "stress_level": 2, "offset": null, "side": null, "proc_width": 4.0, "proc_surface": "unpaved", "proc_smoothness": null, "proc_oneway": "no", "proc_sidepath": null, "proc_highway": "service", "proc_maxspeed": null, "proc_traffic_mode_left": null, "proc_traffic_mode_right": null, "proc_separation_left": "no", "proc_separation_right": "no", "proc_buffer_left": null, "proc_buffer_right": null, "proc_mandatory": null, "proc_traffic_sign": null, "fac_width": 0.25, "fac_surface": 0.3, "fac_highway": 1.0, "fac_maxspeed": 1.0, "base_index": 65, "fac_1": 0.27, "fac_2": 1.0, "fac_3": 1.0, "fac_4": 1.0, "data_bonus": "", "data_malus": "narrow width;bad surface", "data_incompleteness": 80.0, "data_missing": "width;surface;smoothness;lit", "data_missing_width": 1.0, "data_missing_surface": 1.0, "data_missing_smoothness": 1.0, "data_missing_maxspeed": null, "data_missing_parking": null, "data_missing_lit": 1.0, "filter_usable": 1, "filter_way_type": "shared traffic", "msoa": "E02004056", "msoa_threshold_score": 0.0, "index_space_syntax_length": 7.8065960462920909, "index_space_syntax": 0.33988826673115446, "index_length": 413.42624205502636, "length": 22.968124558612576, "index_space_syntax_length_norm": -0.63563435871013607 }, "geometry": { "type": "LineString", "coordinates": [ [ -1.3365173, 53.2880459 ], [ -1.3363911, 53.2878538 ] ] } }
]
}
